COPYING
ChangeLog
MANIFEST.in
NEWS
README
setup.py
man/u2f-authenticate.1.adoc
man/u2f-register.1.adoc
python_u2flib_host.egg-info/PKG-INFO
python_u2flib_host.egg-info/SOURCES.txt
python_u2flib_host.egg-info/dependency_links.txt
python_u2flib_host.egg-info/entry_points.txt
python_u2flib_host.egg-info/requires.txt
python_u2flib_host.egg-info/top_level.txt
test/test_exc.py
test/test_hid.py
test/test_hid_transport.py
test/test_reg_auth.py
test/test_soft.py
test/test_u2f.py
test/test_u2f_v2.py
test/test_utils.py
u2flib_host/__init__.py
u2flib_host/appid.py
u2flib_host/authenticate.py
u2flib_host/constants.py
u2flib_host/device.py
u2flib_host/exc.py
u2flib_host/hid_transport.py
u2flib_host/register.py
u2flib_host/soft.py
u2flib_host/u2f.py
u2flib_host/u2f_v2.py
u2flib_host/utils.py
u2flib_host/yubicommon/__init__.py
u2flib_host/yubicommon/compat.py
u2flib_host/yubicommon/setup/__init__.py
u2flib_host/yubicommon/setup/exe.py
u2flib_host/yubicommon/setup/pyinstaller_spec.py
u2flib_host/yubicommon/setup/qt.py